pytest_notification/__init__.py
pytest_notification/notifications.py
pytest_notification/plugin.py
pytest_notification/sound.py
pytest_notification/sounds/README.rst
pytest_notification/sounds/applause.mp3
pytest_notification/sounds/applause.oga
pytest_notification/sounds/buzzer.mp3
pytest_notification/sounds/buzzer.oga
pytest_notification-0.2.0.dist-info/LICENSE
pytest_notification-0.2.0.dist-info/METADATA
pytest_notification-0.2.0.dist-info/WHEEL
pytest_notification-0.2.0.dist-info/entry_points.txt
pytest_notification-0.2.0.dist-info/top_level.txt
pytest_notification-0.2.0.dist-info/RECORD
