Metadata-Version: 2.1
Name: pytest-notification
Version: 0.2.0
Summary: A pytest plugin for sending a desktop notification and playing a sound upon completion of tests
Home-page: https://github.com/rhpvorderman/pytest-notification
Author: Ruben Vorderman
Author-email: r.h.p.vorderman@lumc.nl
License: MIT
Keywords: pytest notification notify notifier message desktop
Platform: UNKNOWN
Classifier: Programming Language :: Python :: 3 :: Only
Classifier: Programming Language :: Python :: 3
Classifier: Programming Language :: Python :: 3.5
Classifier: Programming Language :: Python :: 3.6
Classifier: Programming Language :: Python :: 3.7
Classifier: Programming Language :: Python :: 3.8
Classifier: Intended Audience :: Developers
Classifier: License :: OSI Approved :: MIT License
Classifier: Framework :: Pytest
Requires-Python: >=3.5
Requires-Dist: pytest (>=4)
